{"v":"5.7.4","fr":30,"ip":0,"op":90,"w":400,"h":300,"nm":"math medium","ddd":0,"assets":[],"layers":[{"ddd":0,"ind":1,"ty":4,"nm":"poly0","sr":1,"ks":{"o":{"a":0,"k":64.69096685061231},"r":{"a":1,"k":[{"t":0,"s":[138.26551051810384],"i":{"x":[0.5],"y":[0.5]},"o":{"x":[0.5],"y":[0.5]}},{"t":90,"s":[498.26551051810384]}]},"p":{"a":0,"k":[162.35062536783516,105.59207116719335,0]},"a":{"a":0,"k":[0,0,0]},"s":{"a":0,"k":[100,100,100]}},"ao":0,"shapes":[{"ty":"gr","it":[{"ty":"sr","sy":2,"d":1,"pt":{"a":0,"k":5},"p":{"a":0,"k":[0,0]},"r":{"a":0,"k":0},"or":{"a":0,"k":36.09276594221592},"os":{"a":0,"k":0},"nm":"sr"},{"ty":"st","c":{"a":0,"k":[0.77,0.71,0.99,1]},"o":{"a":0,"k":100},"w":{"a":0,"k":2.4013783233240247},"lc":2,"lj":2,"nm":"st"},{"ty":"tr","p":{"a":0,"k":[0,0]},"a":{"a":0,"k":[0,0]},"s":{"a":0,"k":[100,100]},"r":{"a":0,"k":0},"o":{"a":0,"k":100}}],"nm":"g"}],"ip":0,"op":90,"st":0,"bm":0},{"ddd":0,"ind":2,"ty":4,"nm":"poly1","sr":1,"ks":{"o":{"a":0,"k":39.594551720656455},"r":{"a":1,"k":[{"t":0,"s":[277.5570019427687],"i":{"x":[0.5],"y":[0.5]},"o":{"x":[0.5],"y":[0.5]}},{"t":90,"s":[637.5570019427687]}]},"p":{"a":0,"k":[281.00451001897454,223.60377449775115,0]},"a":{"a":0,"k":[0,0,0]},"s":{"a":0,"k":[100,100,100]}},"ao":0,"shapes":[{"ty":"gr","it":[{"ty":"sr","sy":2,"d":1,"pt":{"a":0,"k":3},"p":{"a":0,"k":[0,0]},"r":{"a":0,"k":0},"or":{"a":0,"k":38.94446043437347},"os":{"a":0,"k":0},"nm":"sr"},{"ty":"st","c":{"a":0,"k":[0.55,0.48,1.0,1]},"o":{"a":0,"k":100},"w":{"a":0,"k":2.0217025380115956},"lc":2,"lj":2,"nm":"st"},{"ty":"tr","p":{"a":0,"k":[0,0]},"a":{"a":0,"k":[0,0]},"s":{"a":0,"k":[100,100]},"r":{"a":0,"k":0},"o":{"a":0,"k":100}}],"nm":"g"}],"ip":0,"op":90,"st":0,"bm":0},{"ddd":0,"ind":3,"ty":4,"nm":"poly2","sr":1,"ks":{"o":{"a":0,"k":44.3287513195537},"r":{"a":1,"k":[{"t":0,"s":[182.16130558401346],"i":{"x":[0.5],"y":[0.5]},"o":{"x":[0.5],"y":[0.5]}},{"t":90,"s":[542.1613055840135]}]},"p":{"a":0,"k":[90.65873879007995,92.46269267052412,0]},"a":{"a":0,"k":[0,0,0]},"s":{"a":0,"k":[100,100,100]}},"ao":0,"shapes":[{"ty":"gr","it":[{"ty":"sr","sy":2,"d":1,"pt":{"a":0,"k":3},"p":{"a":0,"k":[0,0]},"r":{"a":0,"k":0},"or":{"a":0,"k":33.891336468048394},"os":{"a":0,"k":0},"nm":"sr"},{"ty":"st","c":{"a":0,"k":[0.77,0.71,0.99,1]},"o":{"a":0,"k":100},"w":{"a":0,"k":2.3307307339273393},"lc":2,"lj":2,"nm":"st"},{"ty":"tr","p":{"a":0,"k":[0,0]},"a":{"a":0,"k":[0,0]},"s":{"a":0,"k":[100,100]},"r":{"a":0,"k":0},"o":{"a":0,"k":100}}],"nm":"g"}],"ip":0,"op":90,"st":0,"bm":0},{"ddd":0,"ind":4,"ty":4,"nm":"poly3","sr":1,"ks":{"o":{"a":0,"k":42.89958879351616},"r":{"a":1,"k":[{"t":0,"s":[12.473414121195674],"i":{"x":[0.5],"y":[0.5]},"o":{"x":[0.5],"y":[0.5]}},{"t":90,"s":[372.4734141211957]}]},"p":{"a":0,"k":[124.1407135874033,170.5373286525719,0]},"a":{"a":0,"k":[0,0,0]},"s":{"a":0,"k":[100,100,100]}},"ao":0,"shapes":[{"ty":"gr","it":[{"ty":"sr","sy":2,"d":1,"pt":{"a":0,"k":6},"p":{"a":0,"k":[0,0]},"r":{"a":0,"k":0},"or":{"a":0,"k":27.39241777965799},"os":{"a":0,"k":0},"nm":"sr"},{"ty":"st","c":{"a":0,"k":[0.55,0.48,1.0,1]},"o":{"a":0,"k":100},"w":{"a":0,"k":2.05505866673775},"lc":2,"lj":2,"nm":"st"},{"ty":"tr","p":{"a":0,"k":[0,0]},"a":{"a":0,"k":[0,0]},"s":{"a":0,"k":[100,100]},"r":{"a":0,"k":0},"o":{"a":0,"k":100}}],"nm":"g"}],"ip":0,"op":90,"st":0,"bm":0},{"ddd":0,"ind":5,"ty":4,"nm":"nucleus","sr":1,"ks":{"o":{"a":0,"k":70},"r":{"a":0,"k":0},"p":{"a":0,"k":[180.4742666799575,147.80520976055413,0]},"a":{"a":0,"k":[0,0,0]},"s":{"a":0,"k":[100,100,100]}},"ao":0,"shapes":[{"ty":"gr","it":[{"ty":"el","d":1,"s":{"a":0,"k":[10,10]},"p":{"a":0,"k":[0,0]},"nm":"el"},{"ty":"fl","c":{"a":0,"k":[0.55,0.48,1.0,1]},"o":{"a":0,"k":100},"r":1,"nm":"fl"},{"ty":"tr","p":{"a":0,"k":[0,0]},"a":{"a":0,"k":[0,0]},"s":{"a":0,"k":[100,100]},"r":{"a":0,"k":0},"o":{"a":0,"k":100}}],"nm":"g"}],"ip":0,"op":90,"st":0,"bm":0},{"ddd":0,"ind":6,"ty":4,"nm":"orbit0","sr":1,"ks":{"o":{"a":0,"k":70.9758594376035},"r":{"a":1,"k":[{"t":0,"s":[175.81286687403917],"i":{"x":[0.5],"y":[0.5]},"o":{"x":[0.5],"y":[0.5]}},{"t":90,"s":[-184.18713312596083]}]},"p":{"a":0,"k":[180.4742666799575,147.80520976055413,0]},"a":{"a":0,"k":[0,0,0]},"s":{"a":0,"k":[100,100,100]}},"ao":0,"shapes":[{"ty":"gr","it":[{"ty":"el","d":1,"s":{"a":0,"k":[6.09039865154773,5.759739376604557]},"p":{"a":0,"k":[94.82128366548568,0]},"nm":"el"},{"ty":"fl","c":{"a":0,"k":[0.36,0.55,1.0,1]},"o":{"a":0,"k":100},"r":1,"nm":"fl"},{"ty":"tr","p":{"a":0,"k":[0,0]},"a":{"a":0,"k":[0,0]},"s":{"a":0,"k":[100,100]},"r":{"a":0,"k":0},"o":{"a":0,"k":100}}],"nm":"g"}],"ip":0,"op":90,"st":0,"bm":0},{"ddd":0,"ind":7,"ty":4,"nm":"orbit1","sr":1,"ks":{"o":{"a":0,"k":56.590812020003796},"r":{"a":1,"k":[{"t":0,"s":[199.02804010547698],"i":{"x":[0.5],"y":[0.5]},"o":{"x":[0.5],"y":[0.5]}},{"t":90,"s":[559.028040105477]}]},"p":{"a":0,"k":[180.4742666799575,147.80520976055413,0]},"a":{"a":0,"k":[0,0,0]},"s":{"a":0,"k":[100,100,100]}},"ao":0,"shapes":[{"ty":"gr","it":[{"ty":"el","d":1,"s":{"a":0,"k":[7.11155871860683,8.220360924489796]},"p":{"a":0,"k":[76.63476523943245,0]},"nm":"el"},{"ty":"fl","c":{"a":0,"k":[0.77,0.71,0.99,1]},"o":{"a":0,"k":100},"r":1,"nm":"fl"},{"ty":"tr","p":{"a":0,"k":[0,0]},"a":{"a":0,"k":[0,0]},"s":{"a":0,"k":[100,100]},"r":{"a":0,"k":0},"o":{"a":0,"k":100}}],"nm":"g"}],"ip":0,"op":90,"st":0,"bm":0},{"ddd":0,"ind":8,"ty":4,"nm":"orbit2","sr":1,"ks":{"o":{"a":0,"k":71.41968784620985},"r":{"a":1,"k":[{"t":0,"s":[92.40408020094037],"i":{"x":[0.5],"y":[0.5]},"o":{"x":[0.5],"y":[0.5]}},{"t":90,"s":[452.40408020094037]}]},"p":{"a":0,"k":[180.4742666799575,147.80520976055413,0]},"a":{"a":0,"k":[0,0,0]},"s":{"a":0,"k":[100,100,100]}},"ao":0,"shapes":[{"ty":"gr","it":[{"ty":"el","d":1,"s":{"a":0,"k":[7.747516470961273,7.798098703846335]},"p":{"a":0,"k":[45.68698080908507,0]},"nm":"el"},{"ty":"fl","c":{"a":0,"k":[0.77,0.71,0.99,1]},"o":{"a":0,"k":100},"r":1,"nm":"fl"},{"ty":"tr","p":{"a":0,"k":[0,0]},"a":{"a":0,"k":[0,0]},"s":{"a":0,"k":[100,100]},"r":{"a":0,"k":0},"o":{"a":0,"k":100}}],"nm":"g"}],"ip":0,"op":90,"st":0,"bm":0},{"ddd":0,"ind":9,"ty":4,"nm":"bg","sr":1,"ks":{"o":{"a":0,"k":100},"r":{"a":0,"k":0},"p":{"a":0,"k":[0,0,0]},"a":{"a":0,"k":[0,0,0]},"s":{"a":0,"k":[100,100,100]}},"ao":0,"shapes":[{"ty":"gr","it":[{"ty":"rc","d":1,"s":{"a":0,"k":[400,300]},"p":{"a":0,"k":[200.0,150.0]},"r":{"a":0,"k":0},"nm":"rc"},{"ty":"fl","c":{"a":0,"k":[0.05,0.04,0.12,1]},"o":{"a":0,"k":100},"r":1,"nm":"fl"},{"ty":"tr","p":{"a":0,"k":[0,0]},"a":{"a":0,"k":[0,0]},"s":{"a":0,"k":[100,100]},"r":{"a":0,"k":0},"o":{"a":0,"k":100}}],"nm":"g"}],"ip":0,"op":90,"st":0,"bm":0}]}