{"v":"5.7.4","fr":30,"ip":0,"op":90,"w":200,"h":200,"nm":"math small","ddd":0,"assets":[],"layers":[{"ddd":0,"ind":1,"ty":4,"nm":"ring0","sr":1,"ks":{"o":{"a":1,"k":[{"t":0,"s":[36.26076955348253],"i":{"x":[0.6],"y":[1]},"o":{"x":[0.4],"y":[0]}},{"t":45,"s":[42.70296246162616],"i":{"x":[0.6],"y":[1]},"o":{"x":[0.4],"y":[0]}},{"t":90,"s":[23.59451008029282]}]},"r":{"a":0,"k":0},"p":{"a":0,"k":[123.55196062941104,81.43074878491461,0]},"a":{"a":0,"k":[123.55196062941104,81.43074878491461,0]},"s":{"a":1,"k":[{"t":0,"s":[100.0,100.0,100],"i":{"x":[0.6,0.6,0.6],"y":[1,1,1]},"o":{"x":[0.4,0.4,0.4],"y":[0,0,0]}},{"t":45,"s":[100.0,100.0,100],"i":{"x":[0.6,0.6,0.6],"y":[1,1,1]},"o":{"x":[0.4,0.4,0.4],"y":[0,0,0]}},{"t":90,"s":[100.0,100.0,100]}]}},"ao":0,"shapes":[{"ty":"gr","it":[{"ty":"el","d":1,"s":{"a":0,"k":[90.9090909090909,90.9090909090909]},"p":{"a":0,"k":[0,0]},"nm":"el"},{"ty":"st","c":{"a":0,"k":[0.36,0.55,1.0,1]},"o":{"a":0,"k":100},"w":{"a":0,"k":2.745956914848648},"lc":2,"lj":2,"nm":"st"},{"ty":"tr","p":{"a":0,"k":[0,0]},"a":{"a":0,"k":[0,0]},"s":{"a":0,"k":[100,100]},"r":{"a":0,"k":0},"o":{"a":0,"k":100}}],"nm":"g"}],"ip":0,"op":90,"st":0,"bm":0},{"ddd":0,"ind":2,"ty":4,"nm":"ring1","sr":1,"ks":{"o":{"a":1,"k":[{"t":0,"s":[37.17053873464465],"i":{"x":[0.6],"y":[1]},"o":{"x":[0.4],"y":[0]}},{"t":45,"s":[59.63580480660312],"i":{"x":[0.6],"y":[1]},"o":{"x":[0.4],"y":[0]}},{"t":90,"s":[35.117928301915526]}]},"r":{"a":0,"k":0},"p":{"a":0,"k":[123.55196062941104,81.43074878491461,0]},"a":{"a":0,"k":[123.55196062941104,81.43074878491461,0]},"s":{"a":1,"k":[{"t":0,"s":[118.0,118.0,100],"i":{"x":[0.6,0.6,0.6],"y":[1,1,1]},"o":{"x":[0.4,0.4,0.4],"y":[0,0,0]}},{"t":45,"s":[82.0,82.0,100],"i":{"x":[0.6,0.6,0.6],"y":[1,1,1]},"o":{"x":[0.4,0.4,0.4],"y":[0,0,0]}},{"t":90,"s":[118.0,118.0,100]}]}},"ao":0,"shapes":[{"ty":"gr","it":[{"ty":"el","d":1,"s":{"a":0,"k":[181.8181818181818,181.8181818181818]},"p":{"a":0,"k":[0,0]},"nm":"el"},{"ty":"st","c":{"a":0,"k":[0.36,0.55,1.0,1]},"o":{"a":0,"k":100},"w":{"a":0,"k":2.574607904884033},"lc":2,"lj":2,"nm":"st"},{"ty":"tr","p":{"a":0,"k":[0,0]},"a":{"a":0,"k":[0,0]},"s":{"a":0,"k":[100,100]},"r":{"a":0,"k":0},"o":{"a":0,"k":100}}],"nm":"g"}],"ip":0,"op":90,"st":0,"bm":0},{"ddd":0,"ind":3,"ty":4,"nm":"nucleus","sr":1,"ks":{"o":{"a":0,"k":70},"r":{"a":0,"k":0},"p":{"a":0,"k":[113.07916216552258,126.56764483544976,0]},"a":{"a":0,"k":[0,0,0]},"s":{"a":0,"k":[100,100,100]}},"ao":0,"shapes":[{"ty":"gr","it":[{"ty":"el","d":1,"s":{"a":0,"k":[10,10]},"p":{"a":0,"k":[0,0]},"nm":"el"},{"ty":"fl","c":{"a":0,"k":[0.55,0.48,1.0,1]},"o":{"a":0,"k":100},"r":1,"nm":"fl"},{"ty":"tr","p":{"a":0,"k":[0,0]},"a":{"a":0,"k":[0,0]},"s":{"a":0,"k":[100,100]},"r":{"a":0,"k":0},"o":{"a":0,"k":100}}],"nm":"g"}],"ip":0,"op":90,"st":0,"bm":0},{"ddd":0,"ind":4,"ty":4,"nm":"orbit0","sr":1,"ks":{"o":{"a":0,"k":62.81730258837342},"r":{"a":1,"k":[{"t":0,"s":[46.8296951148659],"i":{"x":[0.5],"y":[0.5]},"o":{"x":[0.5],"y":[0.5]}},{"t":90,"s":[-313.1703048851341]}]},"p":{"a":0,"k":[113.07916216552258,126.56764483544976,0]},"a":{"a":0,"k":[0,0,0]},"s":{"a":0,"k":[100,100,100]}},"ao":0,"shapes":[{"ty":"gr","it":[{"ty":"el","d":1,"s":{"a":0,"k":[7.773894032463431,5.908658084459603]},"p":{"a":0,"k":[54.971551682800055,0]},"nm":"el"},{"ty":"fl","c":{"a":0,"k":[0.77,0.71,0.99,1]},"o":{"a":0,"k":100},"r":1,"nm":"fl"},{"ty":"tr","p":{"a":0,"k":[0,0]},"a":{"a":0,"k":[0,0]},"s":{"a":0,"k":[100,100]},"r":{"a":0,"k":0},"o":{"a":0,"k":100}}],"nm":"g"}],"ip":0,"op":90,"st":0,"bm":0},{"ddd":0,"ind":5,"ty":4,"nm":"orbit1","sr":1,"ks":{"o":{"a":0,"k":57.997600173112005},"r":{"a":1,"k":[{"t":0,"s":[19.264535252004862],"i":{"x":[0.5],"y":[0.5]},"o":{"x":[0.5],"y":[0.5]}},{"t":90,"s":[379.26453525200486]}]},"p":{"a":0,"k":[113.07916216552258,126.56764483544976,0]},"a":{"a":0,"k":[0,0,0]},"s":{"a":0,"k":[100,100,100]}},"ao":0,"shapes":[{"ty":"gr","it":[{"ty":"el","d":1,"s":{"a":0,"k":[6.45668616425246,8.481824217364192]},"p":{"a":0,"k":[66.32284271903336,0]},"nm":"el"},{"ty":"fl","c":{"a":0,"k":[0.77,0.71,0.99,1]},"o":{"a":0,"k":100},"r":1,"nm":"fl"},{"ty":"tr","p":{"a":0,"k":[0,0]},"a":{"a":0,"k":[0,0]},"s":{"a":0,"k":[100,100]},"r":{"a":0,"k":0},"o":{"a":0,"k":100}}],"nm":"g"}],"ip":0,"op":90,"st":0,"bm":0},{"ddd":0,"ind":6,"ty":4,"nm":"bg","sr":1,"ks":{"o":{"a":0,"k":100},"r":{"a":0,"k":0},"p":{"a":0,"k":[0,0,0]},"a":{"a":0,"k":[0,0,0]},"s":{"a":0,"k":[100,100,100]}},"ao":0,"shapes":[{"ty":"gr","it":[{"ty":"rc","d":1,"s":{"a":0,"k":[200,200]},"p":{"a":0,"k":[100.0,100.0]},"r":{"a":0,"k":0},"nm":"rc"},{"ty":"fl","c":{"a":0,"k":[0.05,0.04,0.12,1]},"o":{"a":0,"k":100},"r":1,"nm":"fl"},{"ty":"tr","p":{"a":0,"k":[0,0]},"a":{"a":0,"k":[0,0]},"s":{"a":0,"k":[100,100]},"r":{"a":0,"k":0},"o":{"a":0,"k":100}}],"nm":"g"}],"ip":0,"op":90,"st":0,"bm":0}]}